odoo/addons/shipment_advice_planner_toursolver_queue_job/README.rst
odoo/addons/shipment_advice_planner_toursolver_queue_job/__init__.py
odoo/addons/shipment_advice_planner_toursolver_queue_job/__manifest__.py
odoo/addons/shipment_advice_planner_toursolver_queue_job/data/queue_job_channel.xml
odoo/addons/shipment_advice_planner_toursolver_queue_job/data/queue_job_function.xml
odoo/addons/shipment_advice_planner_toursolver_queue_job/i18n/es.po
odoo/addons/shipment_advice_planner_toursolver_queue_job/i18n/it.po
odoo/addons/shipment_advice_planner_toursolver_queue_job/i18n/shipment_advice_planner_toursolver_queue_job.pot
odoo/addons/shipment_advice_planner_toursolver_queue_job/models/__init__.py
odoo/addons/shipment_advice_planner_toursolver_queue_job/models/toursolver_task.py
odoo/addons/shipment_advice_planner_toursolver_queue_job/readme/CONTRIBUTORS.rst
odoo/addons/shipment_advice_planner_toursolver_queue_job/readme/DESCRIPTION.rst
odoo/addons/shipment_advice_planner_toursolver_queue_job/static/description/icon.png
odoo/addons/shipment_advice_planner_toursolver_queue_job/static/description/index.html
odoo/addons/shipment_advice_planner_toursolver_queue_job/wizards/__init__.py
odoo/addons/shipment_advice_planner_toursolver_queue_job/wizards/shipment_advice_planner.py
odoo_addon_shipment_advice_planner_toursolver_queue_job-16.0.1.0.0.5.dist-info/METADATA
odoo_addon_shipment_advice_planner_toursolver_queue_job-16.0.1.0.0.5.dist-info/WHEEL
odoo_addon_shipment_advice_planner_toursolver_queue_job-16.0.1.0.0.5.dist-info/top_level.txt
odoo_addon_shipment_advice_planner_toursolver_queue_job-16.0.1.0.0.5.dist-info/RECORD
