Metadata-Version: 2.1
Name: odoo-addon-shipment-advice-planner-toursolver-queue-job
Version: 16.0.1.0.0.5
Summary: Run TourSolver queries in queue jobs
Home-page: https://github.com/OCA/stock-logistics-transport
Author: ACSONE SA/NV,Odoo Community Association (OCA)
Author-email: support@odoo-community.org
License: AGPL-3
Platform: UNKNOWN
Classifier: Programming Language :: Python
Classifier: Framework :: Odoo
Classifier: Framework :: Odoo :: 16.0
Classifier: License :: OSI Approved :: GNU Affero General Public License v3
Requires-Python: >=3.10
Requires-Dist: odoo-addon-queue-job <16.1dev,>=16.0dev
Requires-Dist: odoo-addon-shipment-advice-planner-toursolver <16.1dev,>=16.0dev
Requires-Dist: odoo-addon-web-notify <16.1dev,>=16.0dev
Requires-Dist: odoo <16.1dev,>=16.0a
